sentry_wechatwork/__init__.py
sentry_wechatwork/plugin.py
sentry_wechatwork-0.0.1.dist-info/LICENSE
sentry_wechatwork-0.0.1.dist-info/METADATA
sentry_wechatwork-0.0.1.dist-info/WHEEL
sentry_wechatwork-0.0.1.dist-info/entry_points.txt
sentry_wechatwork-0.0.1.dist-info/top_level.txt
sentry_wechatwork-0.0.1.dist-info/RECORD
