Metadata-Version: 2.1
Name: sentry-wechatwork
Version: 0.0.1
Summary: Plugin for Sentry which allows sending notification via WechatWork messenger.
Home-page: https://github.com/kuainiu/sentry-wechatwork
Author: Allen
Author-email: hi@summic.com
License: MIT
Platform: UNKNOWN
Classifier: Development Status :: 5 - Production/Stable
Classifier: Environment :: Console
Classifier: Intended Audience :: Developers
Classifier: Intended Audience :: System Administrators
Classifier: License :: OSI Approved :: MIT License
Classifier: Operating System :: OS Independent
Classifier: Programming Language :: Python
Classifier: Programming Language :: Python :: 2.7
Classifier: Programming Language :: Python :: Implementation :: CPython
Classifier: Topic :: Software Development :: Bug Tracking
Classifier: Topic :: Software Development :: Quality Assurance
Classifier: Topic :: System :: Monitoring
